pypercrypt/__init__.py
pypercrypt/__main__.py
pypercrypt/main.py
pypercrypt-0.3.1.dist-info/LICENSE
pypercrypt-0.3.1.dist-info/METADATA
pypercrypt-0.3.1.dist-info/WHEEL
pypercrypt-0.3.1.dist-info/entry_points.txt
pypercrypt-0.3.1.dist-info/RECORD
