Metadata-Version: 2.1
Name: pypercrypt
Version: 0.3.1
Summary: pypercrypt uses battle-tested cryptography to encrypt your data with the passphrase of your choice and stores the ciphertext inside a QR code.
Home-page: https://github.com/wolfskaempf/pypercrypt
License: EUPL
Author: Tom Wolfskämpf
Author-email: tom@wolfskaempf.de
Requires-Python: >=3.11,<4.0
Classifier: License :: Other/Proprietary License
Classifier: Programming Language :: Python :: 3
Classifier: Programming Language :: Python :: 3.11
Requires-Dist: cryptography (>=41.0.5,<42.0.0)
Requires-Dist: typer (>=0.9.0,<0.10.0)
